transklate/__init__.py
transklate/transklate.py
transklate-0.1.0.dist-info/METADATA
transklate-0.1.0.dist-info/WHEEL
transklate-0.1.0.dist-info/entry_points.txt
transklate-0.1.0.dist-info/licenses/LICENCE.txt
transklate-0.1.0.dist-info/RECORD
