Metadata-Version: 2.4
Name: transklate
Version: 0.1.0
Summary: Use OCR Tesseract to convert Hebrew PDFs to text files and then translate them.
Author-email: Frédérique Michèle Rey <frederique.rey@hu-berlin.de>
Maintainer-email: Frédérique Michèle Rey <frederique.rey@hu-berlin.de>
License-Expression: MIT
License-File: LICENCE.txt
Keywords: OCR,hebrew,transcribe,translation
Classifier: Programming Language :: Python
Requires-Python: >=3.9
Requires-Dist: alive-progress==3.2.0
Requires-Dist: click==8.1.*
Requires-Dist: deep-translator==1.11.4
Requires-Dist: ironpdf==2025.1.1.1
Requires-Dist: pymupdf==1.25.2
Requires-Dist: pytesseract==0.3.13
Requires-Dist: regex==2024.11.6
